{"word2idx": {"<pad>": 0, "<start>": 1, "<resp>": 2, "<end>": 3, "<unk>": 4, "ct": 5, "pneumonia": 6, "cryptococcal": 7, "cta": 8, "pleura": 9, "-": 10, "sinuses": 11, "contents": 12, "lung": 13, "iv": 14, "axial": 15, "meningioma": 16, "no": 17, "paraganglioma": 18, "image": 19, "immunocompetent": 20, "face": 21, "scan": 22, "?": 23, "an": 24, ",": 25, "with": 26, "yes": 27, "contrast": 28, "and": 29, "skull": 30, "host": 31, "angiography": 32, "neck": 33, "in": 34, "mediastinum": 35}, "idx2word": {"0": "<pad>", "1": "<start>", "2": "<resp>", "3": "<end>", "4": "<unk>", "5": "ct", "6": "pneumonia", "7": "cryptococcal", "8": "cta", "9": "pleura", "10": "-", "11": "sinuses", "12": "contents", "13": "lung", "14": "iv", "15": "axial", "16": "meningioma", "17": "no", "18": "paraganglioma", "19": "image", "20": "immunocompetent", "21": "face", "22": "scan", "23": "?", "24": "an", "25": ",", "26": "with", "27": "yes", "28": "contrast", "29": "and", "30": "skull", "31": "host", "32": "angiography", "33": "neck", "34": "in", "35": "mediastinum"}, "idx": 36}